orange_4cast/CompletionInput.py
orange_4cast/CompletionOutput.py
orange_4cast/FracturesInput.py
orange_4cast/FracturesOutput.py
orange_4cast/InputMixin.py
orange_4cast/OutputMixin.py
orange_4cast/PseudoPointsInput.py
orange_4cast/PseudoPointsOutput.py
orange_4cast/RpcClient.py
orange_4cast/WellAttributesInput.py
orange_4cast/WellAttributesOutput.py
orange_4cast/__init__.py
orange_4cast/utils.py
orange_4cast/icons/completionInput.svg
orange_4cast/icons/completionOutput.svg
orange_4cast/icons/fracturesInput.svg
orange_4cast/icons/fracturesOutput.svg
orange_4cast/icons/mvaPointsInput.svg
orange_4cast/icons/mvaPointsOutput.svg
orange_4cast/icons/wellAttributesInput.svg
orange_4cast/icons/wellAttributesOutput.svg
orange_4cast-1.0.8.dist-info/METADATA
orange_4cast-1.0.8.dist-info/WHEEL
orange_4cast-1.0.8.dist-info/entry_points.txt
orange_4cast-1.0.8.dist-info/top_level.txt
orange_4cast-1.0.8.dist-info/RECORD
