Metadata-Version: 2.1
Name: orange-4cast
Version: 1.0.8
Summary: Orange widgets for interaction with 4Cast
Home-page: UNKNOWN
Author: Rogii Inc.
Author-email: UNKNOWN
License: UNKNOWN
Platform: UNKNOWN
Classifier: Programming Language :: Python :: 3
Classifier: Operating System :: OS Independent
Requires-Dist: zerorpc
